Metadata-Version: 1.0
Name: gif2txt-gif
Version: 0.1
Summary: 把GIF图片字符gif图片
Home-page: UNKNOWN
Author: leon.hu
Author-email: sdcxhuoxiaoqi@126.com
License: MIT
Platform: Linux
